<?xml version="1.0" encoding="UTF-8" standalone="yes"?>
<items>
    <contact xsi:type="contact" xmlns:xsi="http://www.w3.org/2001/XMLSchema-instance">
        <id>2</id>
        <userId>3</userId>
        <contactUserId>1</contactUserId>
        <alias>My big bro</alias>
        <addedAt/>
    </contact>
    <contact xsi:type="contact" xmlns:xsi="http://www.w3.org/2001/XMLSchema-instance">
        <id>5</id>
        <userId>9</userId>
        <contactUserId>7</contactUserId>
        <alias>Stech molingui</alias>
        <addedAt/>
    </contact>
    <contact xsi:type="contact" xmlns:xsi="http://www.w3.org/2001/XMLSchema-instance">
        <id>6</id>
        <userId>9</userId>
        <contactUserId>6</contactUserId>
        <alias>Stech molingui</alias>
        <addedAt/>
    </contact>
    <contact xsi:type="contact" xmlns:xsi="http://www.w3.org/2001/XMLSchema-instance">
        <id>7</id>
        <userId>9</userId>
        <contactUserId>1</contactUserId>
        <alias>Japhet</alias>
        <addedAt/>
    </contact>
    <contact xsi:type="contact" xmlns:xsi="http://www.w3.org/2001/XMLSchema-instance">
        <id>8</id>
        <userId>9</userId>
        <contactUserId>2</contactUserId>
        <alias>Japhet</alias>
        <addedAt/>
    </contact>
</items>
